markdownCreation/__init__.py
markdownCreation-1.0.dist-info/LICENSE
markdownCreation-1.0.dist-info/METADATA
markdownCreation-1.0.dist-info/WHEEL
markdownCreation-1.0.dist-info/top_level.txt
markdownCreation-1.0.dist-info/RECORD
