Metadata-Version: 2.1
Name: markdownCreation
Version: 1.0
Summary: A markdown file creation module for Python!
Home-page: https://github.com/Animenosekai/markdown-creation
Author: Anime no Sekai
Author-email: niichannomail@gmail.com
License: MIT
Download-URL: https://github.com/Animenosekai/markdown-creation/archive/v1.0.0.tar.gz
Keywords: markdown, md, readme, html
Platform: UNKNOWN
Classifier: Development Status :: 4 - Beta
Classifier: License :: OSI Approved :: MIT License
Classifier: Programming Language :: Python :: 3
Classifier: Programming Language :: Python :: 3.4
Classifier: Programming Language :: Python :: 3.5
Classifier: Programming Language :: Python :: 3.6
Classifier: Programming Language :: Python :: 3.7
Classifier: Programming Language :: Python :: 3.8
Classifier: Programming Language :: Python :: 3.9
Requires-Dist: markdown
Requires-Dist: beautifulsoup4
Requires-Dist: htmlmin
